instant_API/__init__.py
instant_API/instantAPI.py
instantAPI-1.0.1.dist-info/LICENSE
instantAPI-1.0.1.dist-info/METADATA
instantAPI-1.0.1.dist-info/WHEEL
instantAPI-1.0.1.dist-info/entry_points.txt
instantAPI-1.0.1.dist-info/top_level.txt
instantAPI-1.0.1.dist-info/RECORD
