Metadata-Version: 2.1
Name: instantAPI
Version: 1.0.1
Summary: instant way to create a flask api for your databases
Home-page: https://github.com/SAVE-POlNT/instantAPI
Author: Mehdi YAHIA CHERIF
License: GPLv3
Platform: UNKNOWN
Classifier: License :: OSI Approved :: GNU General Public License v3 (GPLv3)
Classifier: Programming Language :: Python :: 3
Classifier: Programming Language :: Python :: 3.7
